Metadata-Version: 2.1
Name: uncertainty-wrapper
Version: 0.4.2
Summary: Uncertainty wrapper using estimated Jacobian
Home-page: https://github.com/BreakingBytes/UncertaintyWrapper
Author: Mark Mikofski
Author-email: bwana.marko@yahoo.com
License: UNKNOWN
Platform: UNKNOWN
Requires: numpy (>=1.8)
Requires-Dist: numpy (>=1.8)
